{
  "styles": {
    "colors": [
      {
        "name": "1",
        "token": "1",
        "type": "gradient_linear"
      },
      {
        "name": "2",
        "token": "2",
        "type": "gradient_linear"
      },
      {
        "name": "3",
        "token": "3",
        "type": "gradient_linear"
      },
      {
        "name": "4",
        "token": "4",
        "type": "gradient_linear"
      },
      {
        "name": "linear",
        "token": "linear",
        "type": "gradient_linear"
      },
      {
        "name": "journal  blue linear",
        "token": "journal-blue-linear",
        "type": "gradient_linear"
      },
      {
        "name": "BG/background-1",
        "token": "bg-background-1",
        "type": "solid"
      },
      {
        "name": "BG/on-background-1",
        "token": "bg-on-background-1",
        "type": "solid"
      },
      {
        "name": "Border/default",
        "token": "border-default",
        "type": "solid"
      },
      {
        "name": "Border/hover",
        "token": "border-hover",
        "type": "solid"
      },
      {
        "name": "Main Colors/primary",
        "token": "main-colors-primary",
        "type": "gradient_linear"
      },
      {
        "name": "Main Colors/black",
        "token": "main-colors-black",
        "type": "solid"
      },
      {
        "name": "Main Colors/white",
        "token": "main-colors-white",
        "type": "solid"
      },
      {
        "name": "Main Colors/dark gray",
        "token": "main-colors-dark-gray",
        "type": "solid"
      },
      {
        "name": "Main Colors/medium gray",
        "token": "main-colors-medium-gray",
        "type": "solid"
      },
      {
        "name": "Main Colors/gray",
        "token": "main-colors-gray",
        "type": "solid"
      },
      {
        "name": "Gradients/Sunrise Flame",
        "token": "gradients-sunrise-flame",
        "type": "gradient_linear"
      },
      {
        "name": "Gradients/Arctic Flow",
        "token": "gradients-arctic-flow",
        "type": "gradient_linear"
      },
      {
        "name": "Gradients/Emerald Bloom",
        "token": "gradients-emerald-bloom",
        "type": "gradient_linear"
      },
      {
        "name": "Gradients/Violet Surge",
        "token": "gradients-violet-surge",
        "type": "gradient_linear"
      },
      {
        "name": "Gradients/Crimson Burst",
        "token": "gradients-crimson-burst",
        "type": "gradient_linear"
      },
      {
        "name": "Gradients/Spring Surge",
        "token": "gradients-spring-surge",
        "type": "gradient_linear"
      },
      {
        "name": "Gradients/Midnight Drift",
        "token": "gradients-midnight-drift",
        "type": "gradient_linear"
      },
      {
        "name": "Gradients/Golden Dawn",
        "token": "gradients-golden-dawn",
        "type": "gradient_linear"
      },
      {
        "name": "Surface/primary12",
        "token": "surface-primary12",
        "type": "gradient_linear"
      },
      {
        "name": "Surface/black3",
        "token": "surface-black3",
        "type": "solid"
      },
      {
        "name": "Surface/black6",
        "token": "surface-black6",
        "type": "solid"
      },
      {
        "name": "Surface/yellow12",
        "token": "surface-yellow12",
        "type": "solid"
      },
      {
        "name": "Surface/purple6",
        "token": "surface-purple6",
        "type": "solid"
      },
      {
        "name": "Surface/rose6",
        "token": "surface-rose6",
        "type": "solid"
      },
      {
        "name": "Surface/blue6",
        "token": "surface-blue6",
        "type": "solid"
      },
      {
        "name": "Surface/green6",
        "token": "surface-green6",
        "type": "solid"
      },
      {
        "name": "Surface/negative",
        "token": "surface-negative",
        "type": "solid"
      },
      {
        "name": "Surface/Sunrise Flame10",
        "token": "surface-sunrise-flame10",
        "type": "gradient_linear"
      },
      {
        "name": "Surface/Arctic Flow10",
        "token": "surface-arctic-flow10",
        "type": "gradient_linear"
      },
      {
        "name": "Surface/Crimson Burst10",
        "token": "surface-crimson-burst10",
        "type": "gradient_linear"
      },
      {
        "name": "Content/yellow",
        "token": "content-yellow",
        "type": "solid"
      },
      {
        "name": "Content/purple",
        "token": "content-purple",
        "type": "solid"
      },
      {
        "name": "Content/rose",
        "token": "content-rose",
        "type": "solid"
      },
      {
        "name": "Content/blue",
        "token": "content-blue",
        "type": "solid"
      },
      {
        "name": "Content/green",
        "token": "content-green",
        "type": "solid"
      },
      {
        "name": "Link/blue",
        "token": "link-blue",
        "type": "solid"
      },
      {
        "name": "States/negative",
        "token": "states-negative",
        "type": "solid"
      },
      {
        "name": "Avatars/Default",
        "token": "avatars-default",
        "type": "image",
        "scaleMode": "FILL"
      },
      {
        "name": "Avatars/Rotem",
        "token": "avatars-rotem",
        "type": "image",
        "scaleMode": "FILL"
      },
      {
        "name": "Avatars/Rotem",
        "token": "avatars-rotem",
        "type": "image",
        "scaleMode": "FILL"
      },
      {
        "name": "Avatars/Mark",
        "token": "avatars-mark",
        "type": "image",
        "scaleMode": "FILL"
      },
      {
        "name": "Avatars/Goni",
        "token": "avatars-goni",
        "type": "image",
        "scaleMode": "FILL"
      },
      {
        "name": "Avatars/Abigail",
        "token": "avatars-abigail",
        "type": "image",
        "scaleMode": "FILL"
      },
      {
        "name": "Avatars/Juan",
        "token": "avatars-juan",
        "type": "image",
        "scaleMode": "FILL"
      },
      {
        "name": "Avatars/Emma",
        "token": "avatars-emma",
        "type": "image",
        "scaleMode": "FILL"
      },
      {
        "name": "Avatars/Tan",
        "token": "avatars-tan",
        "type": "image",
        "scaleMode": "FILL"
      },
      {
        "name": "Avatars/Meytal",
        "token": "avatars-meytal",
        "type": "image",
        "scaleMode": "FILL"
      },
      {
        "name": "Avatars/Rochita",
        "token": "avatars-rochita",
        "type": "image",
        "scaleMode": "FILL"
      },
      {
        "name": "Avatars/Crystal",
        "token": "avatars-crystal",
        "type": "image",
        "scaleMode": "FILL"
      },
      {
        "name": "Avatars/Emily Ciavolino",
        "token": "avatars-emily-ciavolino",
        "type": "image",
        "scaleMode": "FILL"
      },
      {
        "name": "Avatars/Netta",
        "token": "avatars-netta",
        "type": "image",
        "scaleMode": "FILL"
      },
      {
        "name": "Avatars/Johal",
        "token": "avatars-johal",
        "type": "image",
        "scaleMode": "FILL"
      },
      {
        "name": "Avatars/Elina",
        "token": "avatars-elina",
        "type": "image",
        "scaleMode": "FILL"
      },
      {
        "name": "Avatars/Lupo",
        "token": "avatars-lupo",
        "type": "image",
        "scaleMode": "FILL"
      },
      {
        "name": "Avatars/shirly",
        "token": "avatars-shirly",
        "type": "image",
        "scaleMode": "FILL"
      },
      {
        "name": "Avatars/Molly",
        "token": "avatars-molly",
        "type": "image",
        "scaleMode": "CROP"
      },
      {
        "name": "Avatars/Orr",
        "token": "avatars-orr",
        "type": "image",
        "scaleMode": "FILL"
      },
      {
        "name": "Avatars/Lucy Colgan",
        "token": "avatars-lucy-colgan",
        "type": "image",
        "scaleMode": "FILL"
      },
      {
        "name": "Avatars/Alex",
        "token": "avatars-alex",
        "type": "image",
        "scaleMode": "CROP"
      },
      {
        "name": "Avatars/Dana Morgenstern",
        "token": "avatars-dana-morgenstern",
        "type": "image",
        "scaleMode": "FILL"
      },
      {
        "name": "Avatars/Boaz Arad",
        "token": "avatars-boaz-arad",
        "type": "image",
        "scaleMode": "FILL"
      },
      {
        "name": "Avatars/Amir",
        "token": "avatars-amir",
        "type": "image",
        "scaleMode": "FILL"
      },
      {
        "name": "Avatars/Niv",
        "token": "avatars-niv",
        "type": "image",
        "scaleMode": "FILL"
      },
      {
        "name": "Avatars/Eran",
        "token": "avatars-eran",
        "type": "image",
        "scaleMode": "FILL"
      },
      {
        "name": "Avatars/Royn",
        "token": "avatars-royn",
        "type": "image",
        "scaleMode": "FILL"
      },
      {
        "name": "Avatars/Roy",
        "token": "avatars-roy",
        "type": "image",
        "scaleMode": "FILL"
      },
      {
        "name": "Avatars/Dan",
        "token": "avatars-dan",
        "type": "image",
        "scaleMode": "FILL"
      },
      {
        "name": "Avatars/Shani",
        "token": "avatars-shani",
        "type": "image",
        "scaleMode": "FILL"
      },
      {
        "name": "Avatars/Daniel",
        "token": "avatars-daniel",
        "type": "image",
        "scaleMode": "FILL"
      },
      {
        "name": "Avatars/Noy",
        "token": "avatars-noy",
        "type": "image",
        "scaleMode": "FILL"
      },
      {
        "name": "Avatars/Oren",
        "token": "avatars-oren",
        "type": "image",
        "scaleMode": "CROP"
      },
      {
        "name": "Avatars/Lauren",
        "token": "avatars-lauren",
        "type": "image",
        "scaleMode": "FILL"
      },
      {
        "name": "Avatars/Paola",
        "token": "avatars-paola",
        "type": "image",
        "scaleMode": "FIT"
      },
      {
        "name": "Avatars/Michelle",
        "token": "avatars-michelle",
        "type": "image",
        "scaleMode": "CROP"
      },
      {
        "name": "Avatars/Guy",
        "token": "avatars-guy",
        "type": "image",
        "scaleMode": "FILL"
      }
    ],
    "textStyles": [
      {
        "name": "Web/Display/Dsiplay: Bold",
        "token": "web-display-dsiplay-bold",
        "type": "text",
        "fontFamily": "Fustat",
        "fontWeight": "700",
        "fontSize": "41px",
        "lineHeight": "46px",
        "letterSpacing": "0.5%"
      },
      {
        "name": "Web/Display/Dsiplay: Medium",
        "token": "web-display-dsiplay-medium",
        "type": "text",
        "fontFamily": "Fustat",
        "fontWeight": "500",
        "fontSize": "41px",
        "lineHeight": "46px",
        "letterSpacing": "0.5%"
      },
      {
        "name": "Web/Display/Dsiplay: Regular",
        "token": "web-display-dsiplay-regular",
        "type": "text",
        "fontFamily": "Fustat",
        "fontWeight": "400",
        "fontSize": "41px",
        "lineHeight": "46px",
        "letterSpacing": "0.5%"
      },
      {
        "name": "Web/H1/H1: Bold",
        "token": "web-h1-h1-bold",
        "type": "text",
        "fontFamily": "Fustat",
        "fontWeight": "700",
        "fontSize": "36px",
        "lineHeight": "42px",
        "letterSpacing": "0.5%"
      },
      {
        "name": "Web/H1/H1: Medium",
        "token": "web-h1-h1-medium",
        "type": "text",
        "fontFamily": "Fustat",
        "fontWeight": "500",
        "fontSize": "36px",
        "lineHeight": "42px",
        "letterSpacing": "0.5%"
      },
      {
        "name": "Web/H1/H1: Regular",
        "token": "web-h1-h1-regular",
        "type": "text",
        "fontFamily": "Fustat",
        "fontWeight": "400",
        "fontSize": "36px",
        "lineHeight": "42px",
        "letterSpacing": "0.5%"
      },
      {
        "name": "Web/H2/H2: Bold",
        "token": "web-h2-h2-bold",
        "type": "text",
        "fontFamily": "Fustat",
        "fontWeight": "700",
        "fontSize": "32px",
        "lineHeight": "38px",
        "letterSpacing": "0.5%"
      },
      {
        "name": "Web/H2/H2: Medium",
        "token": "web-h2-h2-medium",
        "type": "text",
        "fontFamily": "Fustat",
        "fontWeight": "500",
        "fontSize": "32px",
        "lineHeight": "38px",
        "letterSpacing": "0.5%"
      },
      {
        "name": "Web/H2/H2: Regular",
        "token": "web-h2-h2-regular",
        "type": "text",
        "fontFamily": "Fustat",
        "fontWeight": "400",
        "fontSize": "32px",
        "lineHeight": "38px",
        "letterSpacing": "0.5%"
      },
      {
        "name": "Web/H3/H3: Bold",
        "token": "web-h3-h3-bold",
        "type": "text",
        "fontFamily": "Fustat",
        "fontWeight": "700",
        "fontSize": "29px",
        "lineHeight": "34px",
        "letterSpacing": "0.5%"
      },
      {
        "name": "Web/H3/H3: Medium",
        "token": "web-h3-h3-medium",
        "type": "text",
        "fontFamily": "Fustat",
        "fontWeight": "500",
        "fontSize": "29px",
        "lineHeight": "34px",
        "letterSpacing": "0.5%"
      },
      {
        "name": "Web/H3/H3: Regular",
        "token": "web-h3-h3-regular",
        "type": "text",
        "fontFamily": "Fustat",
        "fontWeight": "400",
        "fontSize": "29px",
        "lineHeight": "34px",
        "letterSpacing": "0.5%"
      },
      {
        "name": "Web/H4/H4: Bold",
        "token": "web-h4-h4-bold",
        "type": "text",
        "fontFamily": "Fustat",
        "fontWeight": "700",
        "fontSize": "26px",
        "lineHeight": "32px",
        "letterSpacing": "0.5%"
      },
      {
        "name": "Web/H4/H4: Medium",
        "token": "web-h4-h4-medium",
        "type": "text",
        "fontFamily": "Fustat",
        "fontWeight": "500",
        "fontSize": "26px",
        "lineHeight": "32px",
        "letterSpacing": "0.5%"
      },
      {
        "name": "Web/H4/H4: Regular",
        "token": "web-h4-h4-regular",
        "type": "text",
        "fontFamily": "Fustat",
        "fontWeight": "400",
        "fontSize": "26px",
        "lineHeight": "32px",
        "letterSpacing": "0.5%"
      },
      {
        "name": "Web/Body large/Body large: Bold",
        "token": "web-body-large-body-large-bold",
        "type": "text",
        "fontFamily": "Fustat",
        "fontWeight": "700",
        "fontSize": "23px",
        "lineHeight": "30px",
        "letterSpacing": "0.5%"
      },
      {
        "name": "Web/Body large/Body large: Medium",
        "token": "web-body-large-body-large-medium",
        "type": "text",
        "fontFamily": "Fustat",
        "fontWeight": "500",
        "fontSize": "23px",
        "lineHeight": "30px",
        "letterSpacing": "0%"
      },
      {
        "name": "Web/Body large/Body large: Regular",
        "token": "web-body-large-body-large-regular",
        "type": "text",
        "fontFamily": "Fustat",
        "fontWeight": "400",
        "fontSize": "23px",
        "lineHeight": "30px",
        "letterSpacing": "0.5%"
      },
      {
        "name": "Web/Body medium/Body medium: Bold",
        "token": "web-body-medium-body-medium-bold",
        "type": "text",
        "fontFamily": "Fustat",
        "fontWeight": "700",
        "fontSize": "20px",
        "lineHeight": "28px",
        "letterSpacing": "0.5%"
      },
      {
        "name": "Web/Body medium/Body medium: Medium",
        "token": "web-body-medium-body-medium-medium",
        "type": "text",
        "fontFamily": "Fustat",
        "fontWeight": "500",
        "fontSize": "20px",
        "lineHeight": "28px",
        "letterSpacing": "0.5%"
      },
      {
        "name": "Web/Body medium/Body medium: Regular",
        "token": "web-body-medium-body-medium-regular",
        "type": "text",
        "fontFamily": "Fustat",
        "fontWeight": "400",
        "fontSize": "20px",
        "lineHeight": "26px",
        "letterSpacing": "0.5%"
      },
      {
        "name": "Web/Body small/Body small: Bold",
        "token": "web-body-small-body-small-bold",
        "type": "text",
        "fontFamily": "Fustat",
        "fontWeight": "700",
        "fontSize": "18px",
        "lineHeight": "26px",
        "letterSpacing": "0.5%"
      },
      {
        "name": "Web/Body small/Body small: Medium",
        "token": "web-body-small-body-small-medium",
        "type": "text",
        "fontFamily": "Fustat",
        "fontWeight": "500",
        "fontSize": "18px",
        "lineHeight": "28px",
        "letterSpacing": "0.5%"
      },
      {
        "name": "Web/Body small/Body small: Regular",
        "token": "web-body-small-body-small-regular",
        "type": "text",
        "fontFamily": "Fustat",
        "fontWeight": "400",
        "fontSize": "18px",
        "lineHeight": "26px",
        "letterSpacing": "0.5%"
      },
      {
        "name": "Web/Caption large/Caption large: Bold",
        "token": "web-caption-large-caption-large-bold",
        "type": "text",
        "fontFamily": "Fustat",
        "fontWeight": "700",
        "fontSize": "16px",
        "lineHeight": "22px",
        "letterSpacing": "0.5%"
      },
      {
        "name": "Web/Caption large/Caption large: Medium",
        "token": "web-caption-large-caption-large-medium",
        "type": "text",
        "fontFamily": "Fustat",
        "fontWeight": "500",
        "fontSize": "16px",
        "lineHeight": "22px",
        "letterSpacing": "0.5%"
      },
      {
        "name": "Web/Caption large/Caption large: Regular",
        "token": "web-caption-large-caption-large-regular",
        "type": "text",
        "fontFamily": "Fustat",
        "fontWeight": "400",
        "fontSize": "16px",
        "lineHeight": "22px",
        "letterSpacing": "0.5%"
      },
      {
        "name": "Web/Caption medium/Caption medium: SemiBold",
        "token": "web-caption-medium-caption-medium-semibold",
        "type": "text",
        "fontFamily": "Fustat",
        "fontWeight": "600",
        "fontSize": "14px",
        "lineHeight": "18px",
        "letterSpacing": "0.5%"
      },
      {
        "name": "Web/Caption medium/Caption medium: Medium",
        "token": "web-caption-medium-caption-medium-medium",
        "type": "text",
        "fontFamily": "Fustat",
        "fontWeight": "500",
        "fontSize": "14px",
        "lineHeight": "18px",
        "letterSpacing": "0.5%"
      },
      {
        "name": "Web/Caption medium/Caption medium: Regular",
        "token": "web-caption-medium-caption-medium-regular",
        "type": "text",
        "fontFamily": "Fustat",
        "fontWeight": "400",
        "fontSize": "14px",
        "lineHeight": "18px",
        "letterSpacing": "0.5%"
      },
      {
        "name": "Web/Caption small/Caption small: SemiBold",
        "token": "web-caption-small-caption-small-semibold",
        "type": "text",
        "fontFamily": "Fustat",
        "fontWeight": "600",
        "fontSize": "13px",
        "lineHeight": "18px",
        "letterSpacing": "0.5%"
      },
      {
        "name": "Web/Caption small/Caption small: Medium",
        "token": "web-caption-small-caption-small-medium",
        "type": "text",
        "fontFamily": "Fustat",
        "fontWeight": "500",
        "fontSize": "13px",
        "lineHeight": "18px",
        "letterSpacing": "0.5%"
      },
      {
        "name": "Web/Caption small/Caption small: Regular",
        "token": "web-caption-small-caption-small-regular",
        "type": "text",
        "fontFamily": "Fustat",
        "fontWeight": "400",
        "fontSize": "13px",
        "lineHeight": "18px",
        "letterSpacing": "0.5%"
      },
      {
        "name": "Web/Caption xsmall/Caption xsmall: SemiBold",
        "token": "web-caption-xsmall-caption-xsmall-semibold",
        "type": "text",
        "fontFamily": "Fustat",
        "fontWeight": "600",
        "fontSize": "11px",
        "lineHeight": "14px",
        "letterSpacing": "0.5%"
      },
      {
        "name": "Web/Caption xsmall/Caption xsmall: Medium",
        "token": "web-caption-xsmall-caption-xsmall-medium",
        "type": "text",
        "fontFamily": "Fustat",
        "fontWeight": "500",
        "fontSize": "11px",
        "lineHeight": "14px",
        "letterSpacing": "0.5%"
      },
      {
        "name": "Web/Caption xsmall/Caption xsmall: Regular",
        "token": "web-caption-xsmall-caption-xsmall-regular",
        "type": "text",
        "fontFamily": "Fustat",
        "fontWeight": "400",
        "fontSize": "11px",
        "lineHeight": "14px",
        "letterSpacing": "0.5%"
      },
      {
        "name": "Mobile/Display XL/Strong",
        "token": "mobile-display-xl-strong",
        "type": "text",
        "fontFamily": "Work Sans",
        "fontWeight": "600",
        "fontSize": "40px",
        "lineHeight": "48px",
        "letterSpacing": "0%"
      },
      {
        "name": "Mobile/Display/Strong",
        "token": "mobile-display-strong",
        "type": "text",
        "fontFamily": "Work Sans",
        "fontWeight": "600",
        "fontSize": "32px",
        "lineHeight": "48px",
        "letterSpacing": "0%"
      },
      {
        "name": "Mobile/Title/Strong",
        "token": "mobile-title-strong",
        "type": "text",
        "fontFamily": "Work Sans",
        "fontWeight": "600",
        "fontSize": "24px",
        "lineHeight": "36px",
        "letterSpacing": "0%"
      },
      {
        "name": "Mobile/Title/Regular",
        "token": "mobile-title-regular",
        "type": "text",
        "fontFamily": "Work Sans",
        "fontWeight": "400",
        "fontSize": "24px",
        "lineHeight": "36px",
        "letterSpacing": "0%"
      },
      {
        "name": "Mobile/Headline/Strong",
        "token": "mobile-headline-strong",
        "type": "text",
        "fontFamily": "Work Sans",
        "fontWeight": "600",
        "fontSize": "20px",
        "lineHeight": "32px",
        "letterSpacing": "0%"
      },
      {
        "name": "Mobile/Headline/Regular",
        "token": "mobile-headline-regular",
        "type": "text",
        "fontFamily": "Work Sans",
        "fontWeight": "400",
        "fontSize": "20px",
        "lineHeight": "32px",
        "letterSpacing": "0%"
      },
      {
        "name": "Mobile/Body XLarge/Strong",
        "token": "mobile-body-xlarge-strong",
        "type": "text",
        "fontFamily": "Work Sans",
        "fontWeight": "600",
        "fontSize": "18px",
        "lineHeight": "28px",
        "letterSpacing": "0%"
      },
      {
        "name": "Mobile/Body XLarge/Regular",
        "token": "mobile-body-xlarge-regular",
        "type": "text",
        "fontFamily": "Work Sans",
        "fontWeight": "400",
        "fontSize": "18px",
        "lineHeight": "28px",
        "letterSpacing": "0%"
      },
      {
        "name": "Mobile/Body Large/Strong",
        "token": "mobile-body-large-strong",
        "type": "text",
        "fontFamily": "Work Sans",
        "fontWeight": "600",
        "fontSize": "16px",
        "lineHeight": "22px",
        "letterSpacing": "0%"
      },
      {
        "name": "Mobile/Body Large/Medium",
        "token": "mobile-body-large-medium",
        "type": "text",
        "fontFamily": "Work Sans",
        "fontWeight": "500",
        "fontSize": "16px",
        "lineHeight": "22px",
        "letterSpacing": "0%"
      },
      {
        "name": "Mobile/Body/Semibold",
        "token": "mobile-body-semibold",
        "type": "text",
        "fontFamily": "Work Sans",
        "fontWeight": "600",
        "fontSize": "14px",
        "lineHeight": "22px",
        "letterSpacing": "0%"
      },
      {
        "name": "Mobile/Body/Medium",
        "token": "mobile-body-medium",
        "type": "text",
        "fontFamily": "Work Sans",
        "fontWeight": "500",
        "fontSize": "14px",
        "lineHeight": "22px",
        "letterSpacing": "0%"
      },
      {
        "name": "Mobile/Body/Regular",
        "token": "mobile-body-regular",
        "type": "text",
        "fontFamily": "Work Sans",
        "fontWeight": "400",
        "fontSize": "14px",
        "lineHeight": "22px",
        "letterSpacing": "0%"
      },
      {
        "name": "Mobile/Caption/strong",
        "token": "mobile-caption-strong",
        "type": "text",
        "fontFamily": "Work Sans",
        "fontWeight": "600",
        "fontSize": "12px",
        "lineHeight": "18px",
        "letterSpacing": "0%"
      },
      {
        "name": "Mobile/Caption/Medium",
        "token": "mobile-caption-medium",
        "type": "text",
        "fontFamily": "Work Sans",
        "fontWeight": "500",
        "fontSize": "12px",
        "lineHeight": "18px",
        "letterSpacing": "0%"
      },
      {
        "name": "Mobile/Caption/Regular",
        "token": "mobile-caption-regular",
        "type": "text",
        "fontFamily": "Work Sans",
        "fontWeight": "400",
        "fontSize": "12px",
        "lineHeight": "18px",
        "letterSpacing": "0%"
      },
      {
        "name": "Mobile/Caption small/strong",
        "token": "mobile-caption-small-strong",
        "type": "text",
        "fontFamily": "Work Sans",
        "fontWeight": "600",
        "fontSize": "11px",
        "lineHeight": "18px",
        "letterSpacing": "0%"
      },
      {
        "name": "Mobile/Caption small/medium",
        "token": "mobile-caption-small-medium",
        "type": "text",
        "fontFamily": "Work Sans",
        "fontWeight": "500",
        "fontSize": "11px",
        "lineHeight": "18px",
        "letterSpacing": "0%"
      }
    ],
    "effectStyles": [
      {
        "name": "1",
        "token": "1",
        "type": "effect",
        "value": "box-shadow: 0px 4px 20px 0px rgba(0, 0, 0, 0.06)",
        "effects": [
          {
            "type": "glass"
          },
          {
            "type": "drop-shadow",
            "x": 0,
            "y": 4,
            "blur": 20,
            "spread": 0,
            "color": "rgba(0, 0, 0, 0.06)"
          }
        ]
      },
      {
        "name": "2",
        "token": "2",
        "type": "effect",
        "value": "box-shadow: 0px 4px 4px 0px rgba(0, 0, 0, 0.25)",
        "effects": [
          {
            "type": "glass"
          },
          {
            "type": "drop-shadow",
            "x": 0,
            "y": 4,
            "blur": 4,
            "spread": 0,
            "color": "rgba(0, 0, 0, 0.25)"
          }
        ]
      },
      {
        "name": "4",
        "token": "4",
        "type": "effect",
        "value": "box-shadow: 0px 4px 20px 0px rgba(0, 0, 0, 0.06)",
        "effects": [
          {
            "type": "glass"
          },
          {
            "type": "drop-shadow",
            "x": 0,
            "y": 4,
            "blur": 20,
            "spread": 0,
            "color": "rgba(0, 0, 0, 0.06)"
          }
        ]
      },
      {
        "name": "shadow/heavy",
        "token": "shadow-heavy",
        "type": "effect",
        "value": "box-shadow: 0px 0px 16px 0px rgba(0, 0, 0, 0.15)",
        "effects": [
          {
            "type": "drop-shadow",
            "x": 0,
            "y": 0,
            "blur": 16,
            "spread": 0,
            "color": "rgba(0, 0, 0, 0.15)"
          }
        ]
      },
      {
        "name": "shadow/light",
        "token": "shadow-light",
        "type": "effect",
        "value": "box-shadow: 0px 0px 12px 0px rgba(0, 0, 0, 0.11)",
        "effects": [
          {
            "type": "drop-shadow",
            "x": 0,
            "y": 0,
            "blur": 12,
            "spread": 0,
            "color": "rgba(0, 0, 0, 0.11)"
          }
        ]
      },
      {
        "name": "primary shadow/heavey",
        "token": "primary-shadow-heavey",
        "type": "effect",
        "value": "box-shadow: 0px 0px 16px 0px rgba(19, 130, 243, 0.32)",
        "effects": [
          {
            "type": "drop-shadow",
            "x": 0,
            "y": 0,
            "blur": 16,
            "spread": 0,
            "color": "rgba(19, 130, 243, 0.32)"
          }
        ]
      },
      {
        "name": "primary shadow/light",
        "token": "primary-shadow-light",
        "type": "effect",
        "value": "box-shadow: 0px 0px 8px 0px rgba(19, 130, 243, 0.18)",
        "effects": [
          {
            "type": "drop-shadow",
            "x": 0,
            "y": 0,
            "blur": 8,
            "spread": 0,
            "color": "rgba(19, 130, 243, 0.18)"
          }
        ]
      },
      {
        "name": "22/18/9/20",
        "token": "22-18-9-20",
        "type": "effect",
        "value": "box-shadow: 0px 4px 20px 0px rgba(0, 0, 0, 0.06)",
        "effects": [
          {
            "type": "glass"
          },
          {
            "type": "drop-shadow",
            "x": 0,
            "y": 4,
            "blur": 20,
            "spread": 0,
            "color": "rgba(0, 0, 0, 0.06)"
          }
        ]
      }
    ],
    "gridStyles": [
      {
        "name": "Desktop",
        "token": "desktop",
        "type": "grid",
        "grids": [
          {
            "pattern": "columns",
            "count": 12,
            "gutter": 24,
            "margin": 24
          }
        ]
      },
      {
        "name": "Mobile",
        "token": "mobile",
        "type": "grid",
        "grids": [
          {
            "pattern": "columns",
            "count": 4,
            "gutter": 16,
            "margin": 16
          }
        ]
      }
    ]
  }
}